Metadata-Version: 2.3
Name: just-semantic-search-meili
Version: 2.5.0
Summary: Semantic and hybrid search with meilisearch (CPU version)
License: Apache-2.0
Keywords: python,llm,science,review,hybrid search,semantic search,cpu
Author: Anton Kulaga
Author-email: antonkulaga@gmail.com
Requires-Python: >=3.10,<3.15
Classifier: Development Status :: 3 - Alpha
Classifier: Intended Audience :: Developers
Classifier: License :: OSI Approved :: Apache Software License
Classifier: Operating System :: MacOS :: MacOS X
Classifier: Operating System :: Microsoft :: Windows
Classifier: Operating System :: Unix
Classifier: Programming Language :: Python :: 3
Classifier: Programming Language :: Python :: 3.10
Classifier: Programming Language :: Python :: 3.11
Classifier: Programming Language :: Python :: 3.12
Classifier: Programming Language :: Python :: 3.13
Requires-Dist: just-semantic-search
Requires-Dist: meilisearch-python-sdk (>=4.3.0)
Requires-Dist: rich (>=13.9.4)
Requires-Dist: tenacity (>=9.0.0)
Requires-Dist: typer (>=0.9.0)
